{
    "WorkflowType": "RequestPromotion",
    "States": [
        {
            "Name": "Start",
            "DisplayName": "Start",
            "InitialState": true,
            "OnEntryStateAction": "StatefullWorkFlow.Test,StatefullWorkFlow.Test.Services.WriteToConsoleService,OnEntryStateAction",
            "OnExitStateAction": "StatefullWorkFlow.Test,StatefullWorkFlow.Test.Services.WriteToConsoleService,OnExitStateAction"
        },
        {
            "Name": "ManagerConsult",
            "DisplayName": "Manager Consult",
            "InitialState": false,
            "OnEntryStateAction": "StatefullWorkFlow.Test,StatefullWorkFlow.Test.Services.WriteToConsoleService,OnEntryStateAction",
            "OnExitStateAction": "StatefullWorkFlow.Test,StatefullWorkFlow.Test.Services.WriteToConsoleService,OnExitStateAction"
        },
        {
            "Name": "RequestPromotionForm",
            "DisplayName": "Request Promotion Form",
            "InitialState": false,
            "OnEntryStateAction": "StatefullWorkFlow.Test,StatefullWorkFlow.Test.Services.WriteToConsoleService,OnEntryStateAction",
            "OnExitStateAction": "StatefullWorkFlow.Test,StatefullWorkFlow.Test.Services.WriteToConsoleService,OnExitStateAction"
        },
        {
            "Name": "ManagerReview",
            "DisplayName": "Manager Review",
            "InitialState": false,
            "OnEntryStateAction": "StatefullWorkFlow.Test,StatefullWorkFlow.Test.Services.WriteToConsoleService,OnEntryStateAction",
            "OnExitStateAction": "StatefullWorkFlow.Test,StatefullWorkFlow.Test.Services.WriteToConsoleService,OnExitStateAction"
        },
        {
            "Name": "DirectorReview",
            "DisplayName": "Director Review",
            "InitialState": false,
            "OnEntryStateAction": "StatefullWorkFlow.Test,StatefullWorkFlow.Test.Services.WriteToConsoleService,OnEntryStateAction",
            "OnExitStateAction": "StatefullWorkFlow.Test,StatefullWorkFlow.Test.Services.WriteToConsoleService,OnExitStateAction"
        },
        {
            "Name": "PromotionDenied",
            "DisplayName": "Promotion Denied",
            "InitialState": false,
            "OnEntryStateAction": "StatefullWorkFlow.Test,StatefullWorkFlow.Test.Services.WriteToConsoleService,OnEntryStateAction",
            "OnExitStateAction": "StatefullWorkFlow.Test,StatefullWorkFlow.Test.Services.WriteToConsoleService,OnExitStateAction"
        },
        {
            "Name": "Promoted",
            "DisplayName": "Promoted",
            "InitialState": false,
            "OnEntryStateAction": "StatefullWorkFlow.Test,StatefullWorkFlow.Test.Services.WriteToConsoleService,OnEntryStateAction",
            "OnExitStateAction": "StatefullWorkFlow.Test,StatefullWorkFlow.Test.Services.WriteToConsoleService,OnExitStateAction"
        }
    ],
    "StateActivities": [
        {
            "State": "Start",
            "Activities": "RequestPromotionForm"
        },
        {
            "State": "RequestPromotionForm",
            "Activities": "EnterDataToPromotionForm"
        },
        {
            "State": "RequestPromotionForm",
            "Activities": "SubmitPromotionForm"
        },
        {
            "State": "ManagerReview",
            "Activities": "ReviewPromotionForm"
        },
        {
            "State": "ManagerReview",
            "Activities": "ManagerDenyPromotion"
        },
        {
            "State": "ManagerReview",
            "Activities": "ManagerApprovePromotion"
        },
        {
            "State": "DirectorReview",
            "Activities": "ReviewPromotionForm"
        },
        {
            "State": "DirectorReview",
            "Activities": "DirectorDenyPromotion"
        },
        {
            "State": "DirectorReview",
            "Activities": "DirectorApprovePromotion"
        },
        {
            "State": "PromotionDenied",
            "Activities": "Cry"
        },
        {
            "State": "Promoted",
            "Activities": "Celebrate"
        },
        {
            "State": "Promoted",
            "Activities": "CongragulateApplicant"
        }
    ],
    "Activities": [
        {
            "Name": "RequestPromotionForm",
            "DisplayName": "Request Promotion Form"
        },
        {
            "Name": "EnterDataToPromotionForm",
            "DisplayName": "Enter Data To Promotion Form"
        },
        {
            "Name": "SubmitPromotionForm",
            "DisplayName": "Submit Promotion Form"
        },
        {
            "Name": "ReviewPromotionForm",
            "DisplayName": "Review Promotion Form"
        },
        {
            "Name": "ManagerDenyPromotion",
            "DisplayName": "Manager Deny Promotion"
        },
        {
            "Name": "ManagerApprovePromotion",
            "DisplayName": "Manager Approve Promotion"
        },
        {
            "Name": "DirectorDenyPromotion",
            "DisplayName": "Director Deny Promotion"
        },
        {
            "Name": "DirectorApprovePromotion",
            "DisplayName": "Director Approve Promotion"
        },
        {
            "Name": "CongragulateApplicant",
            "DisplayName": "Congragulate Applicant"
        },
        {
            "Name": "Cry",
            "DisplayName": "Cry"
        },
        {
            "Name": "Celebrate",
            "DisplayName": "Celebrate"
        }
    ],
    "Triggers": [
        {
            "Name": "DesirePromotion",
            "DisplayName": "Desire Promotion"
        },
        {
            "Name": "RequestInfo",
            "DisplayName": "Request Info"
        },
        {
            "Name": "Complete",
            "DisplayName": "Complete"
        },
        {
            "Name": "Approve",
            "DisplayName": "Approve"
        },
        {
            "Name": "Deny",
            "DisplayName": "Deny"
        }
    ],
    "StateConfigs": [
        {
            "State": "Start",
            "Trigger": "DesirePromotion",
            "TargetState": "ManagerConsult"
        },
        {
            "State": "ManagerConsult",
            "Trigger": "RequestInfo",
            "TargetState": "RequestPromotionForm"
        },
        {
            "State": "RequestPromotionForm",
            "Trigger": "Complete",
            "TargetState": "ManagerReview"
        },
        {
            "State": "ManagerReview",
            "Trigger": "Deny",
            "TargetState": "PromotionDenied"
        },
        {
            "State": "ManagerReview",
            "Trigger": "Approve",
            "TargetState": "DirectorReview"
        },
        {
            "State": "DirectorReview",
            "Trigger": "Deny",
            "TargetState": "PromotionDenied"
        },
        {
            "State": "DirectorReview",
            "Trigger": "Approve",
            "TargetState": "Promoted"
        }
    ]
}
