[
  {
    "Id": 1,
    "WorkflowId": 1,
    "DisplayName": "Request Promotion Form",
    "AuthorisedRoles": [ "", "" ],
    "AuthorisedUsers": [ "", "" ]
  },
  {
    "Id": 2,
    "WorkflowId": 1,
    "DisplayName": "Enter Data To Promotion Form",
    "AuthorisedRoles": [ "", "" ],
    "AuthorisedUsers": [ "", "" ]
  },
  {
    "Id": 3,
    "WorkflowId": 1,
    "DisplayName": "Submit Promotion Form",
    "AuthorisedRoles": [ "", "" ],
    "AuthorisedUsers": [ "", "" ]
  },
  {
    "Id": 4,
    "WorkflowId": 1,
    "DisplayName": "Manager Review Promotion Form",
    "AuthorisedRoles": [ "", "" ],
    "AuthorisedUsers": [ "", "" ]
  },
  {
    "Id": 5,
    "WorkflowId": 1,
    "DisplayName": "Manager Deny Promotion",
    "AuthorisedRoles": [ "", "" ],
    "AuthorisedUsers": [ "", "" ]
  },
  {
    "Id": 6,
    "WorkflowId": 1,
    "DisplayName": "Manager Approve Promotion",
    "AuthorisedRoles": [ "", "" ],
    "AuthorisedUsers": [ "", "" ]
  },
  {
    "Id": 7,
    "WorkflowId": 1,
    "DisplayName": "Director Deny Promotion",
    "AuthorisedRoles": [ "", "" ],
    "AuthorisedUsers": [ "", "" ]
  },
  {
    "Id": 8,
    "WorkflowId": 1,
    "DisplayName": "Director Approve Promotion",
    "AuthorisedRoles": [ "", "" ],
    "AuthorisedUsers": [ "", "" ]
  },
  {
    "Id": 9,
    "WorkflowId": 1,
    "DisplayName": "Congragulate Applicant",
    "AuthorisedRoles": [ "", "" ],
    "AuthorisedUsers": [ "", "" ]
  },
  {
    "Id": 10,
    "WorkflowId": 1,
    "DisplayName": "Cry",
    "AuthorisedRoles": [ "", "" ],
    "AuthorisedUsers": [ "", "" ]
  },
  {
    "Id": 11,
    "WorkflowId": 1,
    "DisplayName": "Celebrate",
    "AuthorisedRoles": [ "", "" ],
    "AuthorisedUsers": [ "", "" ]
  },
  {
    "Id": 12,
    "WorkflowId": 1,
    "DisplayName": "Console Applicant",
    "AuthorisedRoles": [ "", "" ],
    "AuthorisedUsers": [ "", "" ]
  },
  {
    "Id": 13,
    "WorkflowId": 1,
    "DisplayName": "Director Review Promotion Form",
    "AuthorisedRoles": [ "", "" ],
    "AuthorisedUsers": [ "", "" ]
  }
]
